{"Temperature": ["float", []], "NumNodes": ["int", [47538]], "Iteration": ["int", [1, 2, 3, 4, 5, 6, 7, 8, 9, 10, 11, 12, 13, 14, 15, 16, 17, 18, 19, 20, 21]], "scene": "Deezer-HU", "TimeAttractiveForces": ["float", []], "TimeCopyBack": ["float", []], "stdout": "../results/Deezer-HU_naive.out", "NumEdges": ["int", []], "Elapsed": ["float", [0.0817045, 0.076639, 0.076217, 0.07845, 0.0765376, 0.0760812, 0.0767951, 0.0763975, 0.0777037, 0.0766243, 0.0766222, 0.0762125, 0.0783199, 0.0764681, 0.0756753, 0.0772484, 0.0774367, 0.0767629, 0.0764037, 0.0767004, 0.0751977]], "TimeDisperse": ["float", []], "mode": "naive", "RepulsiveForce": ["float", []], "kValue": ["float", []], "options": ["-r=1", ["../data/deezer_clean_data/HU_edges.csv"]]}