{"Temperature": ["float", [18.1, 18.0819]], "NumNodes": ["int", [32767, 32767]], "Iteration": ["int", [1, 2]], "scene": "tree14", "TimeAttractiveForces": ["float", [0.0013264, 0.0013312]], "Memory": ["float", [2.0, 2.0]], "TimeTraverseAccel": ["float", [0.0102693, 0.0296067]], "TimeCopyBack": ["float", [5.1008e-05, 5.28e-05]], "AvgTimeRepulsiveForce": ["float", [0.011613, 0.021364]], "stdout": "../results/tree14_lbvh.out", "NumEdges": ["int", [32766, 32766]], "Elapsed": ["float", [0.011613, 0.0311149]], "TimeDisperse": ["float", [0.00126586, 0.000112704]], "options": ["-r=1 -dt=tree -trDepth=14", []], "mode": "lbvh", "TimeRepulsiveForce": ["float", [0.011613, 0.0311149]], "kValue": ["float", [0.999908, 0.999908]], "TimeBuildAccel": ["float", [0.0087049, 0.00767702]]}